leetscrape/__init__.py
leetscrape/_constants.py
leetscrape/_helper.py
leetscrape/extract_solution.py
leetscrape/generate_code_stub.py
leetscrape/models.py
leetscrape/question.py
leetscrape/questions_list.py
leetscrape/scripts.py
leetscrape/utils.py
leetscrape-1.0.0.dist-info/entry_points.txt
leetscrape-1.0.0.dist-info/LICENSE
leetscrape-1.0.0.dist-info/METADATA
leetscrape-1.0.0.dist-info/WHEEL
leetscrape-1.0.0.dist-info/RECORD
