Metadata-Version: 2.1
Name: leetscrape
Version: 1.0.0
Summary: Introducing LeetScrape - a powerful and efficient Python package designed to scrape problem statements and their topic and company tags, difficulty, test cases, hints, and code stubs from LeetCode.com. Easily download and save LeetCode problems to your local machine, making it convenient for offline practice and studying. It is perfect for anyone preparing for coding interviews. With the LeetScrape, you can boost your coding skills and improve your chances of landing your dream job.
Home-page: https://github.com/nikhil-ravi/LeetScrape
License: MIT
Author: Nikhil Ravi
Author-email: nr337@cornell.edu
Requires-Python: >=3.10,<4.0
Classifier: License :: OSI Approved :: MIT License
Classifier: Programming Language :: Python :: 3
Classifier: Programming Language :: Python :: 3.10
Classifier: Programming Language :: Python :: 3.11
Provides-Extra: file
Requires-Dist: black (>=22.12.0,<23.0.0)
Requires-Dist: docstring-parser (>=0.15,<0.16)
Requires-Dist: markdownify (>=0.11.6,<0.12.0)
Requires-Dist: marko (>=1.2.2,<2.0.0) ; extra == "file"
Requires-Dist: pandas (>=1.5.2,<2.0.0)
Requires-Dist: pydantic (>=1.10.4,<2.0.0)
Requires-Dist: requests (>=2.28.2,<3.0.0)
Requires-Dist: tqdm (>=4.64.1,<5.0.0)
Project-URL: Documentation, https://leetscrape.chowkabhara.com/
Project-URL: Repository, https://github.com/nikhil-ravi/LeetScrape
